benchmarks/__init__.py
benchmarks/tabular_bench.py
benchmarks/vision_bench.py
runml_checks/__init__.py
runml_checks/checks.py
runml_checks/ppscore.py
runml_checks/suites.py
runml_checks/analytics/__init__.py
runml_checks/analytics/anonymous_telemetry.py
runml_checks/core/__init__.py
runml_checks/core/check_json.py
runml_checks/core/check_result.py
runml_checks/core/checks.py
runml_checks/core/condition.py
runml_checks/core/display.py
runml_checks/core/errors.py
runml_checks/core/suite.py
runml_checks/core/check_utils/__init__.py
runml_checks/core/check_utils/class_performance_utils.py
runml_checks/core/check_utils/feature_label_correlation_utils.py
runml_checks/core/check_utils/whole_dataset_drift_utils.py
runml_checks/core/serialization/__init__.py
runml_checks/core/serialization/abc.py
runml_checks/core/serialization/common.py
runml_checks/core/serialization/check_failure/__init__.py
runml_checks/core/serialization/check_failure/html.py
runml_checks/core/serialization/check_failure/ipython.py
runml_checks/core/serialization/check_failure/json.py
runml_checks/core/serialization/check_failure/wandb.py
runml_checks/core/serialization/check_failure/widget.py
runml_checks/core/serialization/check_result/__init__.py
runml_checks/core/serialization/check_result/html.py
runml_checks/core/serialization/check_result/ipython.py
runml_checks/core/serialization/check_result/json.py
runml_checks/core/serialization/check_result/wandb.py
runml_checks/core/serialization/check_result/widget.py
runml_checks/core/serialization/dataframe/__init__.py
runml_checks/core/serialization/dataframe/html.py
runml_checks/core/serialization/dataframe/widget.py
runml_checks/core/serialization/suite_result/__init__.py
runml_checks/core/serialization/suite_result/html.py
runml_checks/core/serialization/suite_result/ipython.py
runml_checks/core/serialization/suite_result/json.py
runml_checks/core/serialization/suite_result/wandb.py
runml_checks/core/serialization/suite_result/widget.py
runml_checks-1.0.0.dist-info/LICENSE
runml_checks-1.0.0.dist-info/METADATA
runml_checks-1.0.0.dist-info/WHEEL
runml_checks-1.0.0.dist-info/top_level.txt
runml_checks-1.0.0.dist-info/RECORD
