Metadata-Version: 2.1
Name: runml-checks
Version: 1.0.0
Summary: Package for validating your machine learning model and data
Home-page: https://github.com/deepchecks/deepchecks
Author: random_trees
Author-email: info@deepchecks.com
License: UNKNOWN
Download-URL: https://github.com/deepchecks/deepchecks/releases/download/1.0.0/deepchecks-1.0.0.tar.gz
Project-URL: Documentation, https://docs.deepchecks.com
Project-URL: Bug Reports, https://github.com/deepchecks/deepchecks
Project-URL: Source, https://github.com/deepchecks/deepchecks
Project-URL: Contribute!, https://github.com/deepchecks/deepchecks/blob/master/CONTRIBUTING.md
Keywords: Software Development,Machine Learning
Platform: UNKNOWN
Classifier: Intended Audience :: Developers
Classifier: Intended Audience :: Science/Research
Classifier: Topic :: Software Development
Classifier: Topic :: Scientific/Engineering
Classifier: License :: OSI Approved :: GNU Affero General Public License v3 or later (AGPLv3+)
Classifier: Programming Language :: Python :: 3
Classifier: Programming Language :: Python :: 3.6
Classifier: Programming Language :: Python :: 3.7
Classifier: Programming Language :: Python :: 3.8
Classifier: Programming Language :: Python :: 3.9
Classifier: Programming Language :: Python :: 3.10
License-File: LICENSE
Requires-Dist: pandas (>=1.1.5)
Requires-Dist: numpy (>=1.19)
Requires-Dist: scikit-learn (>=0.23.2)
Requires-Dist: jsonpickle (>=2)
Requires-Dist: PyNomaly (>=0.3.3)
Requires-Dist: typing-extensions (>=3.7.4.3)
Requires-Dist: tqdm (>=4.62.3)
Requires-Dist: category-encoders (>=2.3.0)
Requires-Dist: statsmodels (>=0.11.0)
Requires-Dist: scipy (>=1.4.1)
Requires-Dist: plotly (==5.5.0)
Requires-Dist: matplotlib (>=3.3.4)
Requires-Dist: dataclasses (>=0.6) ; python_version < "3.7"
Requires-Dist: ipython (<8,>=5.5.0) ; python_version < "3.8"
Requires-Dist: ipykernel (>=4.10.1) ; python_version < "3.8"
Requires-Dist: ipywidgets (>=7.5.0) ; python_version < "3.8"
Requires-Dist: importlib-resources (>=1.3) ; python_version < "3.9"
Requires-Dist: ipython (<8,>=7.15.0) ; python_version >= "3.8"
Requires-Dist: ipykernel (>=5.3.0) ; python_version >= "3.8"
Requires-Dist: ipywidgets (>=7.6.5) ; python_version >= "3.8"
Provides-Extra: vision
Requires-Dist: pytorch-ignite (>=0.4.8) ; extra == 'vision'
Requires-Dist: opencv-python (>=4.5.5.62) ; extra == 'vision'
Requires-Dist: albumentations (>=1.1.0) ; extra == 'vision'
Requires-Dist: imgaug (>=0.4.0) ; extra == 'vision'
Requires-Dist: requests (>=2.22.0) ; extra == 'vision'
Requires-Dist: seaborn (>=0.1.0) ; extra == 'vision'
Requires-Dist: imagehash (>=4.0.0) ; extra == 'vision'
